requests_load_balancer/__init__.py
requests_load_balancer/load_balancer.py
requests_load_balancer-0.0.2.dist-info/licenses/LICENSE
requests_load_balancer-0.0.2.dist-info/METADATA
requests_load_balancer-0.0.2.dist-info/WHEEL
requests_load_balancer-0.0.2.dist-info/top_level.txt
requests_load_balancer-0.0.2.dist-info/RECORD
