Metadata-Version: 2.4
Name: requests-load-balancer
Version: 0.0.2
Summary: A Python library for load balancing HTTP requests across multiple hosts with health checking
Author-email: earthshakira <arawkar.shubham08@gmail.com>
License: MIT
Project-URL: Homepage, https://github.com/earthshakira/requests-load-balancer
Project-URL: Repository, https://github.com/earthshakira/requests-load-balancer
Project-URL: Bug Tracker, https://github.com/earthshakira/requests-load-balancer/issues
Keywords: requests,load-balancer,http,client,failover,health-check
Classifier: Development Status :: 3 - Alpha
Classifier: Intended Audience :: Developers
Classifier: License :: OSI Approved :: MIT License
Classifier: Programming Language :: Python :: 3
Classifier: Programming Language :: Python :: 3.7
Classifier: Programming Language :: Python :: 3.8
Classifier: Programming Language :: Python :: 3.9
Classifier: Programming Language :: Python :: 3.10
Classifier: Programming Language :: Python :: 3.11
Classifier: Topic :: Internet :: WWW/HTTP
Classifier: Topic :: Software Development :: Libraries :: Python Modules
Requires-Python: >=3.7
License-File: LICENSE
Requires-Dist: requests>=2.25.0
Dynamic: license-file
